{
  "info": {
    "name": "NestJS Ecommerce API (Full)",
    "schema": "https://schema.getpostman.com/json/collection/v2.1.0/collection.json",
    "_postman_id": "e1f0f0b8-0000-4000-8000-collection-full"
  },
  "item": [
    {
      "name": "Languages",
      "item": [
        {
          "name": "List",
          "request": {
            "method": "GET",
            "url": {
              "raw": "http://localhost:3000/languages",
              "protocol": "http",
              "host": ["localhost"],
              "port": "3000",
              "path": ["languages"]
            }
          }
        },
        {
          "name": "Detail",
          "request": {
            "method": "GET",
            "url": {
              "raw": "http://localhost:3000/languages/en",
              "protocol": "http",
              "host": ["localhost"],
              "port": "3000",
              "path": ["languages", "en"]
            }
          }
        },
        {
          "name": "Create",
          "request": {
            "method": "POST",
            "header": [
              { "key": "Content-Type", "value": "application/json" },
              { "key": "Authorization", "value": "Bearer {{accessToken}}" }
            ],
            "url": {
              "raw": "http://localhost:3000/languages",
              "protocol": "http",
              "host": ["localhost"],
              "port": "3000",
              "path": ["languages"]
            },
            "body": { "mode": "raw", "raw": "{\n  \"id\": \"jp\",\n  \"name\": \"日本語\"\n}" }
          }
        },
        {
          "name": "Update",
          "request": {
            "method": "PUT",
            "header": [
              { "key": "Content-Type", "value": "application/json" },
              { "key": "Authorization", "value": "Bearer {{accessToken}}" }
            ],
            "url": {
              "raw": "http://localhost:3000/languages/en",
              "protocol": "http",
              "host": ["localhost"],
              "port": "3000",
              "path": ["languages", "en"]
            },
            "body": { "mode": "raw", "raw": "{\n  \"name\": \"English\"\n}" }
          }
        },
        {
          "name": "Delete",
          "request": {
            "method": "DELETE",
            "header": [{ "key": "Authorization", "value": "Bearer {{accessToken}}" }],
            "url": {
              "raw": "http://localhost:3000/languages/en",
              "protocol": "http",
              "host": ["localhost"],
              "port": "3000",
              "path": ["languages", "en"]
            }
          }
        }
      ]
    },

    {
      "name": "Auth",
      "item": [
        {
          "name": "Login",
          "request": {
            "method": "POST",
            "header": [{ "key": "Content-Type", "value": "application/json" }],
            "url": {
              "raw": "http://localhost:3000/auth/login",
              "protocol": "http",
              "host": ["localhost"],
              "port": "3000",
              "path": ["auth", "login"]
            },
            "body": { "mode": "raw", "raw": "{\n  \"email\": \"admin@example.com\",\n  \"password\": \"Admin@123\"\n}" }
          }
        },
        {
          "name": "Refresh Token",
          "request": {
            "method": "POST",
            "header": [{ "key": "Content-Type", "value": "application/json" }],
            "url": {
              "raw": "http://localhost:3000/auth/refresh-token",
              "protocol": "http",
              "host": ["localhost"],
              "port": "3000",
              "path": ["auth", "refresh-token"]
            },
            "body": { "mode": "raw", "raw": "{\n  \"refreshToken\": \"{{refreshToken}}\"\n}" }
          }
        }
      ]
    },

    {
      "name": "Users",
      "item": [
        {
          "name": "List",
          "request": {
            "method": "GET",
            "header": [{ "key": "Authorization", "value": "Bearer {{accessToken}}" }],
            "url": {
              "raw": "http://localhost:3000/users?page=1&limit=10",
              "protocol": "http",
              "host": ["localhost"],
              "port": "3000",
              "path": ["users"],
              "query": [
                { "key": "page", "value": "1" },
                { "key": "limit", "value": "10" }
              ]
            }
          }
        },
        {
          "name": "Detail",
          "request": {
            "method": "GET",
            "header": [{ "key": "Authorization", "value": "Bearer {{accessToken}}" }],
            "url": {
              "raw": "http://localhost:3000/users/1",
              "protocol": "http",
              "host": ["localhost"],
              "port": "3000",
              "path": ["users", "1"]
            }
          }
        },
        {
          "name": "Create",
          "request": {
            "method": "POST",
            "header": [
              { "key": "Content-Type", "value": "application/json" },
              { "key": "Authorization", "value": "Bearer {{accessToken}}" }
            ],
            "url": {
              "raw": "http://localhost:3000/users",
              "protocol": "http",
              "host": ["localhost"],
              "port": "3000",
              "path": ["users"]
            },
            "body": {
              "mode": "raw",
              "raw": "{\n  \"email\": \"user1@example.com\",\n  \"name\": \"User 1\",\n  \"phoneNumber\": \"0900000001\",\n  \"avatar\": null,\n  \"status\": \"ACTIVE\",\n  \"password\": \"User@123\",\n  \"roleId\": 2\n}"
            }
          }
        },
        {
          "name": "Update",
          "request": {
            "method": "PUT",
            "header": [
              { "key": "Content-Type", "value": "application/json" },
              { "key": "Authorization", "value": "Bearer {{accessToken}}" }
            ],
            "url": {
              "raw": "http://localhost:3000/users/1",
              "protocol": "http",
              "host": ["localhost"],
              "port": "3000",
              "path": ["users", "1"]
            },
            "body": {
              "mode": "raw",
              "raw": "{\n  \"email\": \"user1@example.com\",\n  \"name\": \"User 1\",\n  \"phoneNumber\": \"0900000001\",\n  \"avatar\": null,\n  \"status\": \"ACTIVE\",\n  \"password\": \"User@123\",\n  \"roleId\": 2\n}"
            }
          }
        },
        {
          "name": "Delete",
          "request": {
            "method": "DELETE",
            "header": [{ "key": "Authorization", "value": "Bearer {{accessToken}}" }],
            "url": {
              "raw": "http://localhost:3000/users/1",
              "protocol": "http",
              "host": ["localhost"],
              "port": "3000",
              "path": ["users", "1"]
            }
          }
        }
      ]
    },

    {
      "name": "Profile",
      "item": [
        {
          "name": "Get Profile",
          "request": {
            "method": "GET",
            "header": [{ "key": "Authorization", "value": "Bearer {{accessToken}}" }],
            "url": {
              "raw": "http://localhost:3000/profile",
              "protocol": "http",
              "host": ["localhost"],
              "port": "3000",
              "path": ["profile"]
            }
          }
        },
        {
          "name": "Update Profile",
          "request": {
            "method": "PUT",
            "header": [
              { "key": "Content-Type", "value": "application/json" },
              { "key": "Authorization", "value": "Bearer {{accessToken}}" }
            ],
            "url": {
              "raw": "http://localhost:3000/profile",
              "protocol": "http",
              "host": ["localhost"],
              "port": "3000",
              "path": ["profile"]
            },
            "body": {
              "mode": "raw",
              "raw": "{\n  \"name\": \"Admin\",\n  \"phoneNumber\": \"0909\",\n  \"avatar\": null\n}"
            }
          }
        },
        {
          "name": "Change Password",
          "request": {
            "method": "PUT",
            "header": [
              { "key": "Content-Type", "value": "application/json" },
              { "key": "Authorization", "value": "Bearer {{accessToken}}" }
            ],
            "url": {
              "raw": "http://localhost:3000/profile/change-password",
              "protocol": "http",
              "host": ["localhost"],
              "port": "3000",
              "path": ["profile", "change-password"]
            },
            "body": {
              "mode": "raw",
              "raw": "{\n  \"password\": \"Admin@123\",\n  \"newPassword\": \"Admin@1234\",\n  \"confirmNewPassword\": \"Admin@1234\"\n}"
            }
          }
        }
      ]
    },

    {
      "name": "Permissions",
      "item": [
        {
          "name": "List",
          "request": {
            "method": "GET",
            "header": [{ "key": "Authorization", "value": "Bearer {{accessToken}}" }],
            "url": {
              "raw": "http://localhost:3000/permissions?page=1&limit=10",
              "protocol": "http",
              "host": ["localhost"],
              "port": "3000",
              "path": ["permissions"],
              "query": [
                { "key": "page", "value": "1" },
                { "key": "limit", "value": "10" }
              ]
            }
          }
        },
        {
          "name": "Detail",
          "request": {
            "method": "GET",
            "header": [{ "key": "Authorization", "value": "Bearer {{accessToken}}" }],
            "url": {
              "raw": "http://localhost:3000/permissions/1",
              "protocol": "http",
              "host": ["localhost"],
              "port": "3000",
              "path": ["permissions", "1"]
            }
          }
        },
        {
          "name": "Create",
          "request": {
            "method": "POST",
            "header": [
              { "key": "Content-Type", "value": "application/json" },
              { "key": "Authorization", "value": "Bearer {{accessToken}}" }
            ],
            "url": {
              "raw": "http://localhost:3000/permissions",
              "protocol": "http",
              "host": ["localhost"],
              "port": "3000",
              "path": ["permissions"]
            },
            "body": {
              "mode": "raw",
              "raw": "{\n  \"name\": \"GET-/products\",\n  \"path\": \"/products\",\n  \"method\": \"GET\",\n  \"description\": \"List products\",\n  \"module\": \"PRODUCTS\"\n}"
            }
          }
        },
        {
          "name": "Update",
          "request": {
            "method": "PUT",
            "header": [
              { "key": "Content-Type", "value": "application/json" },
              { "key": "Authorization", "value": "Bearer {{accessToken}}" }
            ],
            "url": {
              "raw": "http://localhost:3000/permissions/1",
              "protocol": "http",
              "host": ["localhost"],
              "port": "3000",
              "path": ["permissions", "1"]
            },
            "body": {
              "mode": "raw",
              "raw": "{\n  \"name\": \"GET-/products\",\n  \"path\": \"/products\",\n  \"method\": \"GET\",\n  \"description\": \"List products\",\n  \"module\": \"PRODUCTS\"\n}"
            }
          }
        },
        {
          "name": "Delete",
          "request": {
            "method": "DELETE",
            "header": [{ "key": "Authorization", "value": "Bearer {{accessToken}}" }],
            "url": {
              "raw": "http://localhost:3000/permissions/1",
              "protocol": "http",
              "host": ["localhost"],
              "port": "3000",
              "path": ["permissions", "1"]
            }
          }
        }
      ]
    },

    {
      "name": "Roles",
      "item": [
        {
          "name": "List",
          "request": {
            "method": "GET",
            "header": [{ "key": "Authorization", "value": "Bearer {{accessToken}}" }],
            "url": {
              "raw": "http://localhost:3000/roles?page=1&limit=10",
              "protocol": "http",
              "host": ["localhost"],
              "port": "3000",
              "path": ["roles"],
              "query": [
                { "key": "page", "value": "1" },
                { "key": "limit", "value": "10" }
              ]
            }
          }
        },
        {
          "name": "Detail",
          "request": {
            "method": "GET",
            "header": [{ "key": "Authorization", "value": "Bearer {{accessToken}}" }],
            "url": {
              "raw": "http://localhost:3000/roles/1",
              "protocol": "http",
              "host": ["localhost"],
              "port": "3000",
              "path": ["roles", "1"]
            }
          }
        },
        {
          "name": "Create",
          "request": {
            "method": "POST",
            "header": [
              { "key": "Content-Type", "value": "application/json" },
              { "key": "Authorization", "value": "Bearer {{accessToken}}" }
            ],
            "url": {
              "raw": "http://localhost:3000/roles",
              "protocol": "http",
              "host": ["localhost"],
              "port": "3000",
              "path": ["roles"]
            },
            "body": {
              "mode": "raw",
              "raw": "{\n  \"name\": \"SELLER\",\n  \"description\": \"Seller role\",\n  \"isActive\": true\n}"
            }
          }
        },
        {
          "name": "Update",
          "request": {
            "method": "PUT",
            "header": [
              { "key": "Content-Type", "value": "application/json" },
              { "key": "Authorization", "value": "Bearer {{accessToken}}" }
            ],
            "url": {
              "raw": "http://localhost:3000/roles/1",
              "protocol": "http",
              "host": ["localhost"],
              "port": "3000",
              "path": ["roles", "1"]
            },
            "body": {
              "mode": "raw",
              "raw": "{\n  \"name\": \"SELLER\",\n  \"description\": \"Seller role\",\n  \"isActive\": true,\n  \"permissionIds\": [1,2,3]\n}"
            }
          }
        },
        {
          "name": "Delete",
          "request": {
            "method": "DELETE",
            "header": [{ "key": "Authorization", "value": "Bearer {{accessToken}}" }],
            "url": {
              "raw": "http://localhost:3000/roles/1",
              "protocol": "http",
              "host": ["localhost"],
              "port": "3000",
              "path": ["roles", "1"]
            }
          }
        }
      ]
    },

    {
      "name": "Brands",
      "item": [
        {
          "name": "List",
          "request": {
            "method": "GET",
            "url": {
              "raw": "http://localhost:3000/brands?page=1&limit=10",
              "protocol": "http",
              "host": ["localhost"],
              "port": "3000",
              "path": ["brands"],
              "query": [
                { "key": "page", "value": "1" },
                { "key": "limit", "value": "10" }
              ]
            }
          }
        },
        {
          "name": "Detail",
          "request": {
            "method": "GET",
            "url": {
              "raw": "http://localhost:3000/brands/1",
              "protocol": "http",
              "host": ["localhost"],
              "port": "3000",
              "path": ["brands", "1"]
            }
          }
        },
        {
          "name": "Create",
          "request": {
            "method": "POST",
            "header": [
              { "key": "Content-Type", "value": "application/json" },
              { "key": "Authorization", "value": "Bearer {{accessToken}}" }
            ],
            "url": {
              "raw": "http://localhost:3000/brands",
              "protocol": "http",
              "host": ["localhost"],
              "port": "3000",
              "path": ["brands"]
            },
            "body": {
              "mode": "raw",
              "raw": "{\n  \"name\": \"Apple\",\n  \"logo\": \"https://logo.clearbit.com/apple.com\"\n}"
            }
          }
        },
        {
          "name": "Update",
          "request": {
            "method": "PUT",
            "header": [
              { "key": "Content-Type", "value": "application/json" },
              { "key": "Authorization", "value": "Bearer {{accessToken}}" }
            ],
            "url": {
              "raw": "http://localhost:3000/brands/1",
              "protocol": "http",
              "host": ["localhost"],
              "port": "3000",
              "path": ["brands", "1"]
            },
            "body": {
              "mode": "raw",
              "raw": "{\n  \"name\": \"Apple\",\n  \"logo\": \"https://logo.clearbit.com/apple.com\"\n}"
            }
          }
        },
        {
          "name": "Delete",
          "request": {
            "method": "DELETE",
            "header": [{ "key": "Authorization", "value": "Bearer {{accessToken}}" }],
            "url": {
              "raw": "http://localhost:3000/brands/1",
              "protocol": "http",
              "host": ["localhost"],
              "port": "3000",
              "path": ["brands", "1"]
            }
          }
        }
      ]
    },

    {
      "name": "Brand Translations",
      "item": [
        {
          "name": "Create",
          "request": {
            "method": "POST",
            "header": [
              { "key": "Content-Type", "value": "application/json" },
              { "key": "Authorization", "value": "Bearer {{accessToken}}" }
            ],
            "url": {
              "raw": "http://localhost:3000/brand-translations",
              "protocol": "http",
              "host": ["localhost"],
              "port": "3000",
              "path": ["brand-translations"]
            },
            "body": {
              "mode": "raw",
              "raw": "{\n  \"brandId\": 1,\n  \"languageId\": \"vi\",\n  \"name\": \"Apple\",\n  \"description\": \"Mô tả thương hiệu\"\n}"
            }
          }
        },
        {
          "name": "Detail",
          "request": {
            "method": "GET",
            "url": {
              "raw": "http://localhost:3000/brand-translations/1",
              "protocol": "http",
              "host": ["localhost"],
              "port": "3000",
              "path": ["brand-translations", "1"]
            }
          }
        },
        {
          "name": "Update",
          "request": {
            "method": "PUT",
            "header": [
              { "key": "Content-Type", "value": "application/json" },
              { "key": "Authorization", "value": "Bearer {{accessToken}}" }
            ],
            "url": {
              "raw": "http://localhost:3000/brand-translations/1",
              "protocol": "http",
              "host": ["localhost"],
              "port": "3000",
              "path": ["brand-translations", "1"]
            },
            "body": {
              "mode": "raw",
              "raw": "{\n  \"brandId\": 1,\n  \"languageId\": \"vi\",\n  \"name\": \"Apple\",\n  \"description\": \"Mô tả thương hiệu\"\n}"
            }
          }
        },
        {
          "name": "Delete",
          "request": {
            "method": "DELETE",
            "header": [{ "key": "Authorization", "value": "Bearer {{accessToken}}" }],
            "url": {
              "raw": "http://localhost:3000/brand-translations/1",
              "protocol": "http",
              "host": ["localhost"],
              "port": "3000",
              "path": ["brand-translations", "1"]
            }
          }
        }
      ]
    },

    {
      "name": "Categories",
      "item": [
        {
          "name": "List Categories",
          "request": {
            "method": "GET",
            "url": {
              "raw": "http://localhost:3000/categories?lang=vi",
              "protocol": "http",
              "host": ["localhost"],
              "port": "3000",
              "path": ["categories"],
              "query": [{ "key": "lang", "value": "vi" }]
            }
          }
        },
        {
          "name": "Get Category Detail",
          "request": {
            "method": "GET",
            "url": {
              "raw": "http://localhost:3000/categories/1?lang=vi",
              "protocol": "http",
              "host": ["localhost"],
              "port": "3000",
              "path": ["categories", "1"],
              "query": [{ "key": "lang", "value": "vi" }]
            }
          }
        },
        {
          "name": "Create Category",
          "request": {
            "method": "POST",
            "header": [
              { "key": "Content-Type", "value": "application/json" },
              { "key": "Authorization", "value": "Bearer {{accessToken}}" }
            ],
            "url": {
              "raw": "http://localhost:3000/categories",
              "protocol": "http",
              "host": ["localhost"],
              "port": "3000",
              "path": ["categories"]
            },
            "body": {
              "mode": "raw",
              "raw": "{\n  \"name\": \"Gaming\",\n  \"logo\": null,\n  \"parentCategoryId\": null\n}"
            }
          }
        }
      ]
    },

    {
      "name": "Category Translations",
      "item": [
        {
          "name": "Create Category Translation",
          "request": {
            "method": "POST",
            "header": [
              { "key": "Content-Type", "value": "application/json" },
              { "key": "Authorization", "value": "Bearer {{accessToken}}" }
            ],
            "url": {
              "raw": "http://localhost:3000/category-translations",
              "protocol": "http",
              "host": ["localhost"],
              "port": "3000",
              "path": ["category-translations"]
            },
            "body": {
              "mode": "raw",
              "raw": "{\n  \"categoryId\": 1,\n  \"languageId\": \"vi\",\n  \"name\": \"Điện thoại\",\n  \"description\": \"Danh mục điện thoại\"\n}"
            }
          }
        }
      ]
    },

    {
      "name": "Products (Public)",
      "item": [
        {
          "name": "List Products",
          "request": {
            "method": "GET",
            "url": {
              "raw": "http://localhost:3000/products?lang=vi&page=1&limit=10",
              "protocol": "http",
              "host": ["localhost"],
              "port": "3000",
              "path": ["products"],
              "query": [
                { "key": "lang", "value": "vi" },
                { "key": "page", "value": "1" },
                { "key": "limit", "value": "10" }
              ]
            }
          }
        },
        {
          "name": "Get Product Detail",
          "request": {
            "method": "GET",
            "url": {
              "raw": "http://localhost:3000/products/1?lang=vi",
              "protocol": "http",
              "host": ["localhost"],
              "port": "3000",
              "path": ["products", "1"],
              "query": [{ "key": "lang", "value": "vi" }]
            }
          }
        }
      ]
    },

    {
      "name": "Manage Products",
      "item": [
        {
          "name": "Create Product",
          "request": {
            "method": "POST",
            "header": [
              { "key": "Content-Type", "value": "application/json" },
              { "key": "Authorization", "value": "Bearer {{accessToken}}" }
            ],
            "url": {
              "raw": "http://localhost:3000/manage-product/products",
              "protocol": "http",
              "host": ["localhost"],
              "port": "3000",
              "path": ["manage-product", "products"]
            },
            "body": {
              "mode": "raw",
              "raw": "{\n  \"publishedAt\": null,\n  \"name\": \"Sample Product\",\n  \"basePrice\": 100,\n  \"virtualPrice\": 120,\n  \"brandId\": 1,\n  \"images\": [\"https://example.com/img.jpg\"],\n  \"variants\": [{\"value\":\"Color\",\"options\":[\"Red\",\"Blue\"]}],\n  \"categories\": [1],\n  \"skus\": [\n    { \"value\": \"Red\", \"price\": 100, \"stock\": 10, \"image\": \"https://example.com/red.jpg\" },\n    { \"value\": \"Blue\", \"price\": 100, \"stock\": 10, \"image\": \"https://example.com/blue.jpg\" }\n  ]\n}"
            }
          }
        }
      ]
    },

    {
      "name": "Media",
      "item": [
        {
          "name": "Upload Images (local)",
          "request": {
            "method": "POST",
            "header": [{ "key": "Authorization", "value": "Bearer {{accessToken}}" }],
            "url": {
              "raw": "http://localhost:3000/media/images/upload",
              "protocol": "http",
              "host": ["localhost"],
              "port": "3000",
              "path": ["media", "images", "upload"]
            }
          }
        },
        {
          "name": "Serve File (public)",
          "request": {
            "method": "GET",
            "url": {
              "raw": "http://localhost:3000/media/static/sample.jpg",
              "protocol": "http",
              "host": ["localhost"],
              "port": "3000",
              "path": ["media", "static", "sample.jpg"]
            }
          }
        },
        {
          "name": "Get Presigned URL",
          "request": {
            "method": "POST",
            "header": [{ "key": "Content-Type", "value": "application/json" }],
            "url": {
              "raw": "http://localhost:3000/media/images/upload/presigned-url",
              "protocol": "http",
              "host": ["localhost"],
              "port": "3000",
              "path": ["media", "images", "upload", "presigned-url"]
            },
            "body": { "mode": "raw", "raw": "{\n  \"filename\": \"image.jpg\",\n  \"filesize\": 500000\n}" }
          }
        }
      ]
    },

    {
      "name": "Cart",
      "item": [
        {
          "name": "Get Cart",
          "request": {
            "method": "GET",
            "header": [{ "key": "Authorization", "value": "Bearer {{accessToken}}" }],
            "url": {
              "raw": "http://localhost:3000/cart?page=1&limit=10",
              "protocol": "http",
              "host": ["localhost"],
              "port": "3000",
              "path": ["cart"],
              "query": [
                { "key": "page", "value": "1" },
                { "key": "limit", "value": "10" }
              ]
            }
          }
        },
        {
          "name": "Add to Cart",
          "request": {
            "method": "POST",
            "header": [
              { "key": "Content-Type", "value": "application/json" },
              { "key": "Authorization", "value": "Bearer {{accessToken}}" }
            ],
            "url": {
              "raw": "http://localhost:3000/cart",
              "protocol": "http",
              "host": ["localhost"],
              "port": "3000",
              "path": ["cart"]
            },
            "body": {
              "mode": "raw",
              "raw": "{\n  \"skuId\": 1,\n  \"quantity\": 2\n}"
            }
          }
        },
        {
          "name": "Update Cart Item",
          "request": {
            "method": "PUT",
            "header": [
              { "key": "Content-Type", "value": "application/json" },
              { "key": "Authorization", "value": "Bearer {{accessToken}}" }
            ],
            "url": {
              "raw": "http://localhost:3000/cart/1",
              "protocol": "http",
              "host": ["localhost"],
              "port": "3000",
              "path": ["cart", "1"]
            },
            "body": {
              "mode": "raw",
              "raw": "{\n  \"skuId\": 1,\n  \"quantity\": 3\n}"
            }
          }
        },
        {
          "name": "Delete Cart Items",
          "request": {
            "method": "POST",
            "header": [
              { "key": "Content-Type", "value": "application/json" },
              { "key": "Authorization", "value": "Bearer {{accessToken}}" }
            ],
            "url": {
              "raw": "http://localhost:3000/cart/delete",
              "protocol": "http",
              "host": ["localhost"],
              "port": "3000",
              "path": ["cart", "delete"]
            },
            "body": {
              "mode": "raw",
              "raw": "{\n  \"cartItemIds\": [1, 2, 3]\n}"
            }
          }
        }
      ]
    },

    {
      "name": "Orders",
      "item": [
        {
          "name": "List Orders",
          "request": {
            "method": "GET",
            "header": [{ "key": "Authorization", "value": "Bearer {{accessToken}}" }],
            "url": {
              "raw": "http://localhost:3000/orders?page=1&limit=10&status=PENDING_PAYMENT",
              "protocol": "http",
              "host": ["localhost"],
              "port": "3000",
              "path": ["orders"],
              "query": [
                { "key": "page", "value": "1" },
                { "key": "limit", "value": "10" },
                { "key": "status", "value": "PENDING_PAYMENT" }
              ]
            }
          }
        },
        {
          "name": "Create Order",
          "request": {
            "method": "POST",
            "header": [
              { "key": "Content-Type", "value": "application/json" },
              { "key": "Authorization", "value": "Bearer {{accessToken}}" }
            ],
            "url": {
              "raw": "http://localhost:3000/orders",
              "protocol": "http",
              "host": ["localhost"],
              "port": "3000",
              "path": ["orders"]
            },
            "body": {
              "mode": "raw",
              "raw": "[\n  {\n    \"shopId\": 1,\n    \"receiver\": {\n      \"name\": \"Nguyễn Văn A\",\n      \"phone\": \"0901234567\",\n      \"address\": \"123 Đường ABC, Quận 1, TP.HCM\"\n    },\n    \"cartItemIds\": [1, 2, 3]\n  }\n]"
            }
          }
        },
        {
          "name": "Get Order Detail",
          "request": {
            "method": "GET",
            "header": [{ "key": "Authorization", "value": "Bearer {{accessToken}}" }],
            "url": {
              "raw": "http://localhost:3000/orders/1",
              "protocol": "http",
              "host": ["localhost"],
              "port": "3000",
              "path": ["orders", "1"]
            }
          }
        },
        {
          "name": "Cancel Order",
          "request": {
            "method": "PUT",
            "header": [
              { "key": "Content-Type", "value": "application/json" },
              { "key": "Authorization", "value": "Bearer {{accessToken}}" }
            ],
            "url": {
              "raw": "http://localhost:3000/orders/1",
              "protocol": "http",
              "host": ["localhost"],
              "port": "3000",
              "path": ["orders", "1"]
            },
            "body": {
              "mode": "raw",
              "raw": "{}"
            }
          }
        }
      ]
    },

    {
      "name": "Payments",
      "item": [
        {
          "name": "Create",
          "request": {
            "method": "POST",
            "header": [
              { "key": "Content-Type", "value": "application/json" },
              { "key": "Authorization", "value": "Bearer {{accessToken}}" }
            ],
            "url": {
              "raw": "http://localhost:3000/payments",
              "protocol": "http",
              "host": ["localhost"],
              "port": "3000",
              "path": ["payments"]
            },
            "body": {
              "mode": "raw",
              "raw": "{\n  \"orderId\": \"ORDER123\",\n  \"amount\": 100000,\n  \"currency\": \"VND\",\n  \"method\": \"CREDIT_CARD\",\n  \"metadata\": {\n    \"note\": \"test\"\n  }\n}"
            }
          }
        },
        {
          "name": "Process",
          "request": {
            "method": "PUT",
            "header": [{ "key": "Authorization", "value": "Bearer {{accessToken}}" }],
            "url": {
              "raw": "http://localhost:3000/payments/1/process",
              "protocol": "http",
              "host": ["localhost"],
              "port": "3000",
              "path": ["payments", "1", "process"]
            }
          }
        },
        {
          "name": "Detail",
          "request": {
            "method": "GET",
            "header": [{ "key": "Authorization", "value": "Bearer {{accessToken}}" }],
            "url": {
              "raw": "http://localhost:3000/payments/1",
              "protocol": "http",
              "host": ["localhost"],
              "port": "3000",
              "path": ["payments", "1"]
            }
          }
        },
        {
          "name": "List",
          "request": {
            "method": "GET",
            "header": [{ "key": "Authorization", "value": "Bearer {{accessToken}}" }],
            "url": {
              "raw": "http://localhost:3000/payments?page=1&limit=10",
              "protocol": "http",
              "host": ["localhost"],
              "port": "3000",
              "path": ["payments"],
              "query": [
                { "key": "page", "value": "1" },
                { "key": "limit", "value": "10" }
              ]
            }
          }
        }
      ]
    },

    {
      "name": "Conversations",
      "item": [
        {
          "name": "List Conversations",
          "request": {
            "method": "GET",
            "header": [{ "key": "Authorization", "value": "Bearer {{accessToken}}" }],
            "url": {
              "raw": "http://localhost:3000/conversations?page=1&limit=10&type=DIRECT&search=&isArchived=false",
              "protocol": "http",
              "host": ["localhost"],
              "port": "3000",
              "path": ["conversations"],
              "query": [
                { "key": "page", "value": "1" },
                { "key": "limit", "value": "10" },
                { "key": "type", "value": "DIRECT" },
                { "key": "search", "value": "" },
                { "key": "isArchived", "value": "false" }
              ]
            }
          }
        },
        {
          "name": "Get Conversation Stats",
          "request": {
            "method": "GET",
            "header": [{ "key": "Authorization", "value": "Bearer {{accessToken}}" }],
            "url": {
              "raw": "http://localhost:3000/conversations/stats",
              "protocol": "http",
              "host": ["localhost"],
              "port": "3000",
              "path": ["conversations", "stats"]
            }
          }
        },
        {
          "name": "Get Conversation Detail",
          "request": {
            "method": "GET",
            "header": [{ "key": "Authorization", "value": "Bearer {{accessToken}}" }],
            "url": {
              "raw": "http://localhost:3000/conversations/{{conversationId}}",
              "protocol": "http",
              "host": ["localhost"],
              "port": "3000",
              "path": ["conversations", "{{conversationId}}"]
            }
          }
        },
        {
          "name": "Create Direct Conversation",
          "request": {
            "method": "POST",
            "header": [
              { "key": "Content-Type", "value": "application/json" },
              { "key": "Authorization", "value": "Bearer {{accessToken}}" }
            ],
            "url": {
              "raw": "http://localhost:3000/conversations/direct",
              "protocol": "http",
              "host": ["localhost"],
              "port": "3000",
              "path": ["conversations", "direct"]
            },
            "body": {
              "mode": "raw",
              "raw": "{\n  \"recipientId\": 2\n}"
            }
          }
        },
        {
          "name": "Create Group Conversation",
          "request": {
            "method": "POST",
            "header": [
              { "key": "Content-Type", "value": "application/json" },
              { "key": "Authorization", "value": "Bearer {{accessToken}}" }
            ],
            "url": {
              "raw": "http://localhost:3000/conversations/group",
              "protocol": "http",
              "host": ["localhost"],
              "port": "3000",
              "path": ["conversations", "group"]
            },
            "body": {
              "mode": "raw",
              "raw": "{\n  \"name\": \"Nhóm làm việc\",\n  \"description\": \"Nhóm thảo luận công việc\",\n  \"memberIds\": [2, 3, 4],\n  \"avatar\": \"https://example.com/group-avatar.jpg\"\n}"
            }
          }
        },
        {
          "name": "Update Conversation",
          "request": {
            "method": "PUT",
            "header": [
              { "key": "Content-Type", "value": "application/json" },
              { "key": "Authorization", "value": "Bearer {{accessToken}}" }
            ],
            "url": {
              "raw": "http://localhost:3000/conversations/{{conversationId}}",
              "protocol": "http",
              "host": ["localhost"],
              "port": "3000",
              "path": ["conversations", "{{conversationId}}"]
            },
            "body": {
              "mode": "raw",
              "raw": "{\n  \"name\": \"Tên nhóm mới\",\n  \"description\": \"Mô tả mới\",\n  \"avatar\": \"https://example.com/new-avatar.jpg\"\n}"
            }
          }
        },
        {
          "name": "Archive Conversation",
          "request": {
            "method": "POST",
            "header": [{ "key": "Authorization", "value": "Bearer {{accessToken}}" }],
            "url": {
              "raw": "http://localhost:3000/conversations/{{conversationId}}/archive",
              "protocol": "http",
              "host": ["localhost"],
              "port": "3000",
              "path": ["conversations", "{{conversationId}}", "archive"]
            }
          }
        },
        {
          "name": "Leave Conversation",
          "request": {
            "method": "DELETE",
            "header": [{ "key": "Authorization", "value": "Bearer {{accessToken}}" }],
            "url": {
              "raw": "http://localhost:3000/conversations/{{conversationId}}/leave",
              "protocol": "http",
              "host": ["localhost"],
              "port": "3000",
              "path": ["conversations", "{{conversationId}}", "leave"]
            }
          }
        }
      ]
    },

    {
      "name": "Addresses",
      "item": [
        {
          "name": "List Addresses",
          "request": {
            "method": "GET",
            "header": [{ "key": "Authorization", "value": "Bearer {{accessToken}}" }],
            "url": {
              "raw": "http://localhost:3000/addresses?page=1&limit=10&isActive=true",
              "protocol": "http",
              "host": ["localhost"],
              "port": "3000",
              "path": ["addresses"],
              "query": [
                { "key": "page", "value": "1" },
                { "key": "limit", "value": "10" },
                { "key": "isActive", "value": "true" }
              ]
            }
          }
        },
        {
          "name": "Create Address",
          "request": {
            "method": "POST",
            "header": [
              { "key": "Content-Type", "value": "application/json" },
              { "key": "Authorization", "value": "Bearer {{accessToken}}" }
            ],
            "url": {
              "raw": "http://localhost:3000/addresses",
              "protocol": "http",
              "host": ["localhost"],
              "port": "3000",
              "path": ["addresses"]
            },
            "body": {
              "mode": "raw",
              "raw": "{\n  \"name\": \"Nguyễn Văn A\",\n  \"phone\": \"0901234567\",\n  \"provinceId\": \"79\",\n  \"provinceName\": \"Thành phố Hồ Chí Minh\",\n  \"districtId\": \"760\",\n  \"districtName\": \"Quận 1\",\n  \"wardId\": \"26734\",\n  \"wardName\": \"Phường Bến Nghé\",\n  \"detail\": \"123 Đường Nguyễn Huệ\",\n  \"isDefault\": true\n}"
            }
          }
        },
        {
          "name": "Get Address Stats",
          "request": {
            "method": "GET",
            "header": [{ "key": "Authorization", "value": "Bearer {{accessToken}}" }],
            "url": {
              "raw": "http://localhost:3000/addresses/stats",
              "protocol": "http",
              "host": ["localhost"],
              "port": "3000",
              "path": ["addresses", "stats"]
            }
          }
        },
        {
          "name": "Get Default Address",
          "request": {
            "method": "GET",
            "header": [{ "key": "Authorization", "value": "Bearer {{accessToken}}" }],
            "url": {
              "raw": "http://localhost:3000/addresses/default",
              "protocol": "http",
              "host": ["localhost"],
              "port": "3000",
              "path": ["addresses", "default"]
            }
          }
        },
        {
          "name": "Get Address Detail",
          "request": {
            "method": "GET",
            "header": [{ "key": "Authorization", "value": "Bearer {{accessToken}}" }],
            "url": {
              "raw": "http://localhost:3000/addresses/{{addressId}}",
              "protocol": "http",
              "host": ["localhost"],
              "port": "3000",
              "path": ["addresses", "{{addressId}}"]
            }
          }
        },
        {
          "name": "Update Address",
          "request": {
            "method": "PUT",
            "header": [
              { "key": "Content-Type", "value": "application/json" },
              { "key": "Authorization", "value": "Bearer {{accessToken}}" }
            ],
            "url": {
              "raw": "http://localhost:3000/addresses/{{addressId}}",
              "protocol": "http",
              "host": ["localhost"],
              "port": "3000",
              "path": ["addresses", "{{addressId}}"]
            },
            "body": {
              "mode": "raw",
              "raw": "{\n  \"name\": \"Nguyễn Văn A (Updated)\",\n  \"phone\": \"0901234567\",\n  \"detail\": \"456 Đường Nguyễn Huệ (Updated)\"\n}"
            }
          }
        },
        {
          "name": "Set Default Address",
          "request": {
            "method": "PUT",
            "header": [{ "key": "Authorization", "value": "Bearer {{accessToken}}" }],
            "url": {
              "raw": "http://localhost:3000/addresses/{{addressId}}/default",
              "protocol": "http",
              "host": ["localhost"],
              "port": "3000",
              "path": ["addresses", "{{addressId}}", "default"]
            }
          }
        },
        {
          "name": "Delete Address",
          "request": {
            "method": "DELETE",
            "header": [{ "key": "Authorization", "value": "Bearer {{accessToken}}" }],
            "url": {
              "raw": "http://localhost:3000/addresses/{{addressId}}",
              "protocol": "http",
              "host": ["localhost"],
              "port": "3000",
              "path": ["addresses", "{{addressId}}"]
            }
          }
        }
      ]
    },

    {
      "name": "Vouchers",
      "item": [
        {
          "name": "Get Available Vouchers (Public)",
          "request": {
            "method": "GET",
            "url": {
              "raw": "http://localhost:3000/vouchers/available?page=1&limit=10&type=PERCENTAGE",
              "protocol": "http",
              "host": ["localhost"],
              "port": "3000",
              "path": ["vouchers", "available"],
              "query": [
                { "key": "page", "value": "1" },
                { "key": "limit", "value": "10" },
                { "key": "type", "value": "PERCENTAGE" }
              ]
            }
          }
        },
        {
          "name": "Get Voucher by Code",
          "request": {
            "method": "GET",
            "url": {
              "raw": "http://localhost:3000/vouchers/code/WELCOME10",
              "protocol": "http",
              "host": ["localhost"],
              "port": "3000",
              "path": ["vouchers", "code", "WELCOME10"]
            }
          }
        },
        {
          "name": "Get Voucher Detail",
          "request": {
            "method": "GET",
            "header": [{ "key": "Authorization", "value": "Bearer {{accessToken}}" }],
            "url": {
              "raw": "http://localhost:3000/vouchers/{{voucherId}}",
              "protocol": "http",
              "host": ["localhost"],
              "port": "3000",
              "path": ["vouchers", "{{voucherId}}"]
            }
          }
        },
        {
          "name": "Collect Voucher",
          "request": {
            "method": "POST",
            "header": [{ "key": "Authorization", "value": "Bearer {{accessToken}}" }],
            "url": {
              "raw": "http://localhost:3000/vouchers/{{voucherId}}/collect",
              "protocol": "http",
              "host": ["localhost"],
              "port": "3000",
              "path": ["vouchers", "{{voucherId}}", "collect"]
            }
          }
        },
        {
          "name": "Get My Vouchers",
          "request": {
            "method": "GET",
            "header": [{ "key": "Authorization", "value": "Bearer {{accessToken}}" }],
            "url": {
              "raw": "http://localhost:3000/vouchers/my?page=1&limit=10&status=available",
              "protocol": "http",
              "host": ["localhost"],
              "port": "3000",
              "path": ["vouchers", "my"],
              "query": [
                { "key": "page", "value": "1" },
                { "key": "limit", "value": "10" },
                { "key": "status", "value": "available" }
              ]
            }
          }
        },
        {
          "name": "Apply Voucher",
          "request": {
            "method": "POST",
            "header": [
              { "key": "Content-Type", "value": "application/json" },
              { "key": "Authorization", "value": "Bearer {{accessToken}}" }
            ],
            "url": {
              "raw": "http://localhost:3000/vouchers/apply",
              "protocol": "http",
              "host": ["localhost"],
              "port": "3000",
              "path": ["vouchers", "apply"]
            },
            "body": {
              "mode": "raw",
              "raw": "{\n  \"code\": \"WELCOME10\",\n  \"orderAmount\": 500000,\n  \"productIds\": [1, 2, 3]\n}"
            }
          }
        },
        {
          "name": "Get My Voucher Stats",
          "request": {
            "method": "GET",
            "header": [{ "key": "Authorization", "value": "Bearer {{accessToken}}" }],
            "url": {
              "raw": "http://localhost:3000/vouchers/my/stats",
              "protocol": "http",
              "host": ["localhost"],
              "port": "3000",
              "path": ["vouchers", "my", "stats"]
            }
          }
        }
      ]
    },

    {
      "name": "Voucher Management (Admin/Seller)",
      "item": [
        {
          "name": "Create Voucher",
          "request": {
            "method": "POST",
            "header": [
              { "key": "Content-Type", "value": "application/json" },
              { "key": "Authorization", "value": "Bearer {{accessToken}}" }
            ],
            "url": {
              "raw": "http://localhost:3000/vouchers/manage",
              "protocol": "http",
              "host": ["localhost"],
              "port": "3000",
              "path": ["vouchers", "manage"]
            },
            "body": {
              "mode": "raw",
              "raw": "{\n  \"code\": \"NEWSALE20\",\n  \"name\": \"Sale mới 20%\",\n  \"description\": \"Voucher giảm 20% cho đơn hàng từ 300k\",\n  \"type\": \"PERCENTAGE\",\n  \"value\": 20,\n  \"minOrderValue\": 300000,\n  \"maxDiscount\": 100000,\n  \"usageLimit\": 100,\n  \"userUsageLimit\": 1,\n  \"startDate\": \"2024-01-01T00:00:00.000Z\",\n  \"endDate\": \"2024-12-31T23:59:59.000Z\",\n  \"isActive\": true\n}"
            }
          }
        },
        {
          "name": "List Vouchers (Management)",
          "request": {
            "method": "GET",
            "header": [{ "key": "Authorization", "value": "Bearer {{accessToken}}" }],
            "url": {
              "raw": "http://localhost:3000/vouchers/manage?page=1&limit=10&isActive=true",
              "protocol": "http",
              "host": ["localhost"],
              "port": "3000",
              "path": ["vouchers", "manage"],
              "query": [
                { "key": "page", "value": "1" },
                { "key": "limit", "value": "10" },
                { "key": "isActive", "value": "true" }
              ]
            }
          }
        },
        {
          "name": "Get Voucher Stats (Management)",
          "request": {
            "method": "GET",
            "header": [{ "key": "Authorization", "value": "Bearer {{accessToken}}" }],
            "url": {
              "raw": "http://localhost:3000/vouchers/manage/stats",
              "protocol": "http",
              "host": ["localhost"],
              "port": "3000",
              "path": ["vouchers", "manage", "stats"]
            }
          }
        },
        {
          "name": "Update Voucher",
          "request": {
            "method": "PUT",
            "header": [
              { "key": "Content-Type", "value": "application/json" },
              { "key": "Authorization", "value": "Bearer {{accessToken}}" }
            ],
            "url": {
              "raw": "http://localhost:3000/vouchers/manage/{{voucherId}}",
              "protocol": "http",
              "host": ["localhost"],
              "port": "3000",
              "path": ["vouchers", "manage", "{{voucherId}}"]
            },
            "body": {
              "mode": "raw",
              "raw": "{\n  \"name\": \"Sale mới 25% (Updated)\",\n  \"value\": 25,\n  \"maxDiscount\": 150000\n}"
            }
          }
        },
        {
          "name": "Delete Voucher",
          "request": {
            "method": "DELETE",
            "header": [{ "key": "Authorization", "value": "Bearer {{accessToken}}" }],
            "url": {
              "raw": "http://localhost:3000/vouchers/manage/{{voucherId}}",
              "protocol": "http",
              "host": ["localhost"],
              "port": "3000",
              "path": ["vouchers", "manage", "{{voucherId}}"]
            }
          }
        }
      ]
    },
    {
      "name": "AI Assistant",
      "item": [
        {
          "name": "Test AI Assistant (No Auth)",
          "request": {
            "method": "GET",
            "url": {
              "raw": "http://localhost:3000/ai-assistant/test?message=Xin chào! Tôi muốn tìm hiểu về sản phẩm iPhone 15 Pro Max",
              "protocol": "http",
              "host": ["localhost"],
              "port": "3000",
              "path": ["ai-assistant", "test"],
              "query": [
                {
                  "key": "message",
                  "value": "Xin chào! Tôi muốn tìm hiểu về sản phẩm iPhone 15 Pro Max"
                }
              ]
            }
          }
        },
        {
          "name": "Test Streaming (No Auth)",
          "request": {
            "method": "GET",
            "url": {
              "raw": "http://localhost:3000/ai-assistant/test-stream?message=Tôi cần tư vấn laptop cho học sinh",
              "protocol": "http",
              "host": ["localhost"],
              "port": "3000",
              "path": ["ai-assistant", "test-stream"],
              "query": [
                {
                  "key": "message",
                  "value": "Tôi cần tư vấn laptop cho học sinh"
                }
              ]
            }
          }
        },
        {
          "name": "Create AI Conversation",
          "request": {
            "method": "POST",
            "header": [
              { "key": "Content-Type", "value": "application/json" },
              { "key": "Authorization", "value": "Bearer {{accessToken}}" }
            ],
            "url": {
              "raw": "http://localhost:3000/ai-assistant/conversations",
              "protocol": "http",
              "host": ["localhost"],
              "port": "3000",
              "path": ["ai-assistant", "conversations"]
            },
            "body": {
              "mode": "raw",
              "raw": "{\n  \"context\": {\n    \"userPreferences\": {\n      \"categories\": [\"electronics\", \"smartphones\"]\n    }\n  }\n}"
            }
          }
        },
        {
          "name": "Get User Conversations",
          "request": {
            "method": "GET",
            "header": [{ "key": "Authorization", "value": "Bearer {{accessToken}}" }],
            "url": {
              "raw": "http://localhost:3000/ai-assistant/conversations?page=1&limit=10",
              "protocol": "http",
              "host": ["localhost"],
              "port": "3000",
              "path": ["ai-assistant", "conversations"],
              "query": [
                { "key": "page", "value": "1" },
                { "key": "limit", "value": "10" }
              ]
            }
          }
        },
        {
          "name": "Get Conversation Details",
          "request": {
            "method": "GET",
            "header": [{ "key": "Authorization", "value": "Bearer {{accessToken}}" }],
            "url": {
              "raw": "http://localhost:3000/ai-assistant/conversations/{{aiConversationId}}",
              "protocol": "http",
              "host": ["localhost"],
              "port": "3000",
              "path": ["ai-assistant", "conversations", "{{aiConversationId}}"]
            }
          }
        },
        {
          "name": "Send Message to AI",
          "request": {
            "method": "POST",
            "header": [
              { "key": "Content-Type", "value": "application/json" },
              { "key": "Authorization", "value": "Bearer {{accessToken}}" }
            ],
            "url": {
              "raw": "http://localhost:3000/ai-assistant/conversations/{{aiConversationId}}/messages",
              "protocol": "http",
              "host": ["localhost"],
              "port": "3000",
              "path": ["ai-assistant", "conversations", "{{aiConversationId}}", "messages"]
            },
            "body": {
              "mode": "raw",
              "raw": "{\n  \"message\": \"Tôi muốn mua điện thoại iPhone 15 Pro Max. Bạn có thể tư vấn về giá cả và tính năng không?\"\n}"
            }
          }
        },
        {
          "name": "Stream in Conversation",
          "request": {
            "method": "GET",
            "header": [{ "key": "Authorization", "value": "Bearer {{accessToken}}" }],
            "url": {
              "raw": "http://localhost:3000/ai-assistant/conversations/{{aiConversationId}}/stream?message=So sánh iPhone 15 Pro Max với Samsung Galaxy S24 Ultra",
              "protocol": "http",
              "host": ["localhost"],
              "port": "3000",
              "path": ["ai-assistant", "conversations", "{{aiConversationId}}", "stream"],
              "query": [
                {
                  "key": "message",
                  "value": "So sánh iPhone 15 Pro Max với Samsung Galaxy S24 Ultra"
                }
              ]
            }
          }
        },
        {
          "name": "Archive Conversation",
          "request": {
            "method": "PATCH",
            "header": [{ "key": "Authorization", "value": "Bearer {{accessToken}}" }],
            "url": {
              "raw": "http://localhost:3000/ai-assistant/conversations/{{aiConversationId}}/archive",
              "protocol": "http",
              "host": ["localhost"],
              "port": "3000",
              "path": ["ai-assistant", "conversations", "{{aiConversationId}}", "archive"]
            }
          }
        },
        {
          "name": "Delete Conversation",
          "request": {
            "method": "DELETE",
            "header": [{ "key": "Authorization", "value": "Bearer {{accessToken}}" }],
            "url": {
              "raw": "http://localhost:3000/ai-assistant/conversations/{{aiConversationId}}",
              "protocol": "http",
              "host": ["localhost"],
              "port": "3000",
              "path": ["ai-assistant", "conversations", "{{aiConversationId}}"]
            }
          }
        },
        {
          "name": "Search Messages",
          "request": {
            "method": "GET",
            "header": [{ "key": "Authorization", "value": "Bearer {{accessToken}}" }],
            "url": {
              "raw": "http://localhost:3000/ai-assistant/search?q=iPhone&page=1&limit=10",
              "protocol": "http",
              "host": ["localhost"],
              "port": "3000",
              "path": ["ai-assistant", "search"],
              "query": [
                { "key": "q", "value": "iPhone" },
                { "key": "page", "value": "1" },
                { "key": "limit", "value": "10" }
              ]
            }
          }
        },
        {
          "name": "Get AI Stats",
          "request": {
            "method": "GET",
            "header": [{ "key": "Authorization", "value": "Bearer {{accessToken}}" }],
            "url": {
              "raw": "http://localhost:3000/ai-assistant/stats",
              "protocol": "http",
              "host": ["localhost"],
              "port": "3000",
              "path": ["ai-assistant", "stats"]
            }
          }
        }
      ]
    }
  ],
  "variable": [
    { "key": "accessToken", "value": "" },
    { "key": "refreshToken", "value": "" },
    { "key": "conversationId", "value": "" },
    { "key": "messageId", "value": "" },
    { "key": "memberId", "value": "" },
    { "key": "addressId", "value": "" },
    { "key": "voucherId", "value": "" },
    { "key": "aiConversationId", "value": "" }
  ]
}
